[{
  "_id": {
    "$oid": "67eaf59671c9665dad6ea635"
  },
  "idService": {
    "$oid": "67eaef8e91c591e716152d3b"
  },
  "date": {
    "$date": "2025-03-31T00:00:00.000Z"
  },
  "montant": 7500,
  "createdAt": {
    "$date": "2025-03-31T20:05:42.375Z"
  },
  "updatedAt": {
    "$date": "2025-03-31T20:05:42.375Z"
  },
  "__v": 0
},
{
  "_id": {
    "$oid": "67eaf6f571c9665dad6ea638"
  },
  "idService": {
    "$oid": "67eaefc091c591e716152d3d"
  },
  "date": {
    "$date": "2025-03-31T00:00:00.000Z"
  },
  "montant": 20000,
  "createdAt": {
    "$date": "2025-03-31T20:11:33.975Z"
  },
  "updatedAt": {
    "$date": "2025-03-31T20:11:33.975Z"
  },
  "__v": 0
},
{
  "_id": {
    "$oid": "67eaf70a71c9665dad6ea63a"
  },
  "idService": {
    "$oid": "67eaefe691c591e716152d3f"
  },
  "date": {
    "$date": "2025-03-31T00:00:00.000Z"
  },
  "montant": 100000,
  "createdAt": {
    "$date": "2025-03-31T20:11:54.531Z"
  },
  "updatedAt": {
    "$date": "2025-03-31T20:11:54.531Z"
  },
  "__v": 0
},
{
  "_id": {
    "$oid": "67eaf71a71c9665dad6ea63c"
  },
  "idService": {
    "$oid": "67eaf01291c591e716152d41"
  },
  "date": {
    "$date": "2025-03-31T00:00:00.000Z"
  },
  "montant": 140000,
  "createdAt": {
    "$date": "2025-03-31T20:12:10.435Z"
  },
  "updatedAt": {
    "$date": "2025-03-31T20:12:10.435Z"
  },
  "__v": 0
},
{
  "_id": {
    "$oid": "67eaf72b71c9665dad6ea63e"
  },
  "idService": {
    "$oid": "67eaf04591c591e716152d43"
  },
  "date": {
    "$date": "2025-03-31T00:00:00.000Z"
  },
  "montant": 175000,
  "createdAt": {
    "$date": "2025-03-31T20:12:27.278Z"
  },
  "updatedAt": {
    "$date": "2025-03-31T20:12:27.278Z"
  },
  "__v": 0
},
{
  "_id": {
    "$oid": "67eaf73771c9665dad6ea640"
  },
  "idService": {
    "$oid": "67eaf07b91c591e716152d45"
  },
  "date": {
    "$date": "2025-03-31T00:00:00.000Z"
  },
  "montant": 250000,
  "createdAt": {
    "$date": "2025-03-31T20:12:39.546Z"
  },
  "updatedAt": {
    "$date": "2025-03-31T20:12:39.546Z"
  },
  "__v": 0
},
{
  "_id": {
    "$oid": "67eaf74d71c9665dad6ea642"
  },
  "idService": {
    "$oid": "67eaf0b791c591e716152d47"
  },
  "date": {
    "$date": "2025-03-31T00:00:00.000Z"
  },
  "montant": 350000,
  "createdAt": {
    "$date": "2025-03-31T20:13:01.365Z"
  },
  "updatedAt": {
    "$date": "2025-03-31T20:13:01.365Z"
  },
  "__v": 0
},
{
  "_id": {
    "$oid": "67eaf75f71c9665dad6ea644"
  },
  "idService": {
    "$oid": "67eaf20791c591e716152d4d"
  },
  "date": {
    "$date": "2025-03-31T00:00:00.000Z"
  },
  "montant": 550000,
  "createdAt": {
    "$date": "2025-03-31T20:13:19.327Z"
  },
  "updatedAt": {
    "$date": "2025-03-31T20:13:19.327Z"
  },
  "__v": 0
},
{
  "_id": {
    "$oid": "67eaf77471c9665dad6ea646"
  },
  "idService": {
    "$oid": "67eaf0e991c591e716152d49"
  },
  "date": {
    "$date": "2025-03-31T00:00:00.000Z"
  },
  "montant": 1100000,
  "createdAt": {
    "$date": "2025-03-31T20:13:40.095Z"
  },
  "updatedAt": {
    "$date": "2025-03-31T20:13:40.095Z"
  },
  "__v": 0
},
{
  "_id": {
    "$oid": "67eaf78271c9665dad6ea648"
  },
  "idService": {
    "$oid": "67eaf13691c591e716152d4b"
  },
  "date": {
    "$date": "2025-03-31T00:00:00.000Z"
  },
  "montant": 1600000,
  "createdAt": {
    "$date": "2025-03-31T20:13:54.959Z"
  },
  "updatedAt": {
    "$date": "2025-03-31T20:13:54.959Z"
  },
  "__v": 0
}]